{
    "name": "solarized-dark",
    "baseVimTheme": "solarized8",
    "baseVimBackground": "dark",
    "colors": {
        "background": "#002B36",
        "foreground": "#93A1A1",

        "title.background": "#CB4B16",
        "title.foreground": "#93A1A1",

        "editor.background": "#002B36",
        "editor.foreground": "#93A1A1",

        "tabs.background": "#073642",
        "tabs.foreground": "#93A1A1",

        "toolTip.background": "#073642",
        "toolTip.foreground": "#93A1A1",
        "toolTip.border": "#002B36",

        "menu.background": "#073642",
        "menu.foreground": "#93A1A1",
        "menu.border": "#268BD2",

        "contextMenu.background": "#DC322F",
        "contextMenu.foreground": "#93A1A1",
        "contextMenu.border": "#505050",
        "contextMenu.highlight": "#3F4652",

        "sidebar.background": "#1DC322F",
        "sidebar.foreground": "#93A1A1",
        "sidebar.active.background": "#282C34",
        "sidebar.selection.border": "#61afef",

        "statusBar.background": "#002B36",
        "statusBar.foreground": "#93A1A1",

        "highlight.mode.insert.background": "#268BD2",
        "highlight.mode.insert.foreground": "#002B36",

        "highlight.mode.normal.background": "#B58900",
        "highlight.mode.normal.foreground": "#002B36",

        "highlight.mode.operator.background": "#6C71C4",
        "highlight.mode.operator.foreground": "#002B36",

        "highlight.mode.visual.background": "#D33682",
        "highlight.mode.visual.foreground": "#002B36"
    }
}
